mcp_alchemy/__init__.py
mcp_alchemy/server.py
mseep_mcp_alchemy-2025.4.16.110004.dist-info/METADATA
mseep_mcp_alchemy-2025.4.16.110004.dist-info/WHEEL
mseep_mcp_alchemy-2025.4.16.110004.dist-info/entry_points.txt
mseep_mcp_alchemy-2025.4.16.110004.dist-info/licenses/LICENSE
mseep_mcp_alchemy-2025.4.16.110004.dist-info/RECORD
